{
	"description": "项目配置文件。",
	"setting": {
		"urlCheck": false,
		"es6": true,
		"postcss": true,
		"minified": true,
		"newFeature": true
	},
	"compileType": "miniprogram",
	"libVersion": "1.9.93",
	"appid": "wxa13e85f06bd96fe4",
	"projectname": "%E5%B0%8F%E8%AF%BA%E7%9B%B4%E6%92%AD",
	"isGameTourist": false,
	"condition": {
		"search": {
			"current": -1,
			"list": []
		},
		"conversation": {
			"current": -1,
			"list": []
		},
		"game": {
			"currentL": -1,
			"list": []
		},
		"miniprogram": {
			"current": -1,
			"list": []
		}
	}
}